dj_lucide-1.1.12.dist-info/licenses/LICENSE
lucide/__init__.py
lucide/_compat.py
lucide/jinja.py
lucide/lucide.zip
lucide/py.typed
lucide/management/commands/update_lucide_icons.py
lucide/templatetags/__init__.py
lucide/templatetags/lucide.py
dj_lucide-1.1.12.dist-info/METADATA
dj_lucide-1.1.12.dist-info/WHEEL
dj_lucide-1.1.12.dist-info/top_level.txt
dj_lucide-1.1.12.dist-info/RECORD
