Metadata-Version: 2.4
Name: dj-lucide
Version: 1.1.12
Summary: Use lucide in your Django and Jinja templates.
Author-email: David Rydwanski <dr@squies.de>, Francisco Macedo <me@fmacedo.com>
License: MIT
Project-URL: Changelog, https://github.com/vidski/lucide/blob/main/CHANGELOG.md
Project-URL: Repository, https://github.com/vidski/lucide
Keywords: Django
Classifier: Development Status :: 5 - Production/Stable
Classifier: Framework :: Django :: 3.2
Classifier: Framework :: Django :: 4.0
Classifier: Framework :: Django :: 4.1
Classifier: Framework :: Django :: 4.2
Classifier: Framework :: Django :: 5.0
Classifier: Framework :: Django :: 5.1
Classifier: Framework :: Django :: 5.2
Classifier: Intended Audience :: Developers
Classifier: License :: OSI Approved :: MIT License
Classifier: Natural Language :: English
Classifier: Operating System :: OS Independent
Classifier: Programming Language :: Python :: 3 :: Only
Classifier: Programming Language :: Python :: 3.8
Classifier: Programming Language :: Python :: 3.9
Classifier: Programming Language :: Python :: 3.10
Classifier: Programming Language :: Python :: 3.11
Classifier: Programming Language :: Python :: 3.12
Classifier: Programming Language :: Python :: 3.13
Classifier: Programming Language :: Python :: Implementation :: CPython
Classifier: Typing :: Typed
Requires-Python: >=3.8
License-File: LICENSE
Provides-Extra: django
Requires-Dist: django>=2.2; extra == "django"
Provides-Extra: jinja
Requires-Dist: jinja2>=2.8; extra == "jinja"
Dynamic: license-file
